jsonlogic/__init__.py
jsonlogic/classes.py
jsonlogic/errors.py
jsonlogic/jsontypes.py
jsonlogic/operations.py
jsonlogic/py.typed
jsonlogic_py-0.2.1.dist-info/METADATA
jsonlogic_py-0.2.1.dist-info/WHEEL
jsonlogic_py-0.2.1.dist-info/top_level.txt
jsonlogic_py-0.2.1.dist-info/RECORD
