Metadata-Version: 2.4
Name: jsonlogic-py
Version: 0.2.1
Summary: A Python package that emits JSON Logic
Author: Peter Pirkelbauer, Seth Bromberger
Project-URL: Homepage, https://github.com/MetallData/jsonlogic
Project-URL: Issues, https://github.com/MetallData/jsonlogic/issues
Classifier: Development Status :: 3 - Alpha
Classifier: Programming Language :: Python :: 3
Classifier: Intended Audience :: Science/Research
Classifier: License :: OSI Approved :: MIT License
Classifier: Operating System :: OS Independent
Requires-Python: >=3.10
Provides-Extra: dev
Requires-Dist: pytest; extra == "dev"
Requires-Dist: coverage; extra == "dev"
Requires-Dist: json-logic-qubit; extra == "dev"
Requires-Dist: ruff; extra == "dev"
Requires-Dist: mypy; extra == "dev"
